LICENSE
README.rst
pyproject.toml
setup.py
xiver_gpt/XiverGPT.py
xiver_gpt/__init__.py
xiver_gpt/the_s_of_idea.py
xiver_gpt.egg-info/PKG-INFO
xiver_gpt.egg-info/SOURCES.txt
xiver_gpt.egg-info/dependency_links.txt
xiver_gpt.egg-info/requires.txt
xiver_gpt.egg-info/top_level.txt
xiver_gpt/exceptions/NoProvider.py
xiver_gpt/exceptions/__init__.py