Metadata-Version: 2.1
Name: xiver-gpt
Version: 0.0.3b0
Summary: The module Xiver team use to work with gpt.
Home-page: https://github.com/xiver/xiver-gpt
Download-URL: https://github.com/xiver/xiver-gpt/archive/master.zip
Author: GigantPro
Author-email: gigantpro2000@gmail.ru
License: The GPLv3 License (GPLv3)
Classifier: Operating System :: OS Independent
Classifier: Intended Audience :: End Users/Desktop
Classifier: Intended Audience :: Developers
Classifier: Programming Language :: Python
Classifier: Programming Language :: Python :: 3.10
Classifier: Programming Language :: Python :: 3.11
Classifier: Programming Language :: Python :: Implementation :: PyPy
License-File: LICENSE
